mols2grid/__init__.py
mols2grid/_version.py
mols2grid/callbacks.py
mols2grid/datafiles.py
mols2grid/dispatch.py
mols2grid/molgrid.py
mols2grid/select.py
mols2grid/utils.py
mols2grid/widget.py
mols2grid/data/solubility.test.sdf
mols2grid/static/widget.css
mols2grid/static/widget.js
mols2grid/templates/__init__.py
mols2grid/templates/interactive.html
mols2grid/templates/static.html
mols2grid/templates/css/common.css
mols2grid/templates/css/interactive.css
mols2grid/templates/css/static.css
mols2grid/templates/html/common_header.html
mols2grid/templates/html/iframe.html
mols2grid/templates/html/interactive_header.html
mols2grid/templates/js/draw_mol.js
mols2grid/templates/js/filter.js
mols2grid/templates/js/grid_interaction.js
mols2grid/templates/js/interactive.js
mols2grid/templates/js/kernel.js
mols2grid/templates/js/molstorage.js
mols2grid/templates/js/popup.js
mols2grid/templates/js/search.js
mols2grid/templates/js/sort.js
mols2grid/templates/js/callbacks/external_link.js
mols2grid/templates/js/callbacks/show_3d.js
mols2grid-2.2.0.dist-info/METADATA
mols2grid-2.2.0.dist-info/WHEEL
mols2grid-2.2.0.dist-info/licenses/LICENSE
mols2grid-2.2.0.dist-info/RECORD
