Metadata-Version: 2.4
Name: mols2grid
Version: 2.2.0
Summary: Interactive 2D small molecule viewer
Project-URL: Homepage, https://github.com/cbouy/mols2grid
Project-URL: Documentation, https://mols2grid.readthedocs.io/en/latest/
Project-URL: Discussions, https://github.com/cbouy/mols2grid/discussions
Project-URL: Issues, https://github.com/cbouy/mols2grid/issues
Project-URL: Changelog, https://github.com/cbouy/mols2grid/blob/master/CHANGELOG.md
Author-email: Cédric Bouysset <cedric@bouysset.net>
License:                                  Apache License
License-File: LICENSE
Keywords: cheminformatics,chemistry,jupyter,science,widgets
Classifier: Development Status :: 5 - Production/Stable
Classifier: Framework :: Jupyter
Classifier: Intended Audience :: Science/Research
Classifier: Operating System :: OS Independent
Classifier: Programming Language :: Python :: 3
Classifier: Programming Language :: Python :: 3.10
Classifier: Programming Language :: Python :: 3.11
Classifier: Programming Language :: Python :: 3.12
Classifier: Programming Language :: Python :: 3.13
Classifier: Topic :: Scientific/Engineering :: Chemistry
Requires-Python: >=3.10
Requires-Dist: anywidget
Requires-Dist: jinja2
Requires-Dist: numpy
Requires-Dist: pandas
Requires-Dist: rdkit
